epurifier/__init__.py
epurifier/email_checker.py
epurifier/query_yes_or_no.py
epurifier/test2.py
epurifier/test3.py
epurifier/test4.py
epurifier/tezt.py
epurifier/valid_emails.py
epurifier-0.1.1.dist-info/LICENSE
epurifier-0.1.1.dist-info/METADATA
epurifier-0.1.1.dist-info/WHEEL
epurifier-0.1.1.dist-info/entry_points.txt
epurifier-0.1.1.dist-info/top_level.txt
epurifier-0.1.1.dist-info/RECORD
