Metadata-Version: 2.1
Name: epurifier
Version: 0.1.1
Summary: A email verifier for csv files
Home-page: https://github.com/xypnox/email_purifier
Author: xypnox
Author-email: xypnox@gmail.com
License: UNKNOWN
Platform: UNKNOWN
Classifier: Programming Language :: Python :: 3
Classifier: License :: OSI Approved :: GNU General Public License v2 (GPLv2)
Classifier: Operating System :: OS Independent
Requires-Dist: pandas
